LICENSE
README.md
setup.py
lunax/__init__.py
lunax.egg-info/PKG-INFO
lunax.egg-info/SOURCES.txt
lunax.egg-info/dependency_links.txt
lunax.egg-info/requires.txt
lunax.egg-info/top_level.txt
lunax/data_processing/__init__.py
lunax/data_processing/utils.py
lunax/ensembles/__init__.py
lunax/ensembles/hill_climbing.py
lunax/hyper_opt/__init__.py
lunax/hyper_opt/base_tuner.py
lunax/hyper_opt/optuna_tuner.py
lunax/models/__init__.py
lunax/models/base_model.py
lunax/models/nn_models.py
lunax/models/tree_models.py
lunax/models/utils.py
lunax/viz/__init__.py
lunax/viz/eda.py
lunax/xai/__init__.py
lunax/xai/explainer.py
tests/__init__.py
tests/test_model.py
tests/test_opt.py