Metadata-Version: 2.4
Name: lunax
Version: 0.0.11
Summary: A machine learning framework.
Home-page: https://github.com/yangfa-zhang/lunax
Author: yangfa-zhang
Author-email: yangfa1027@gmail.com
License: MIT Licence
Keywords: pip,tabular data
Platform: any
License-File: LICENSE
Requires-Dist: numpy
Requires-Dist: pandas
Requires-Dist: xgboost
Requires-Dist: tabulate
Requires-Dist: python-abc
Requires-Dist: typing
Requires-Dist: scikit-learn
Requires-Dist: optuna
Requires-Dist: lightgbm
Requires-Dist: catboost
Requires-Dist: matplotlib
Requires-Dist: seaborn
Requires-Dist: tabpfn
Requires-Dist: shap
Dynamic: author
Dynamic: author-email
Dynamic: description
Dynamic: home-page
Dynamic: keywords
Dynamic: license
Dynamic: license-file
Dynamic: platform
Dynamic: requires-dist
Dynamic: summary
